hydra_plugins/moai_searchpath_plugin/__init__.py
hydra_plugins/moai_searchpath_plugin/moai_searchpath_plugin.py
hydra_moai_searchpath_plugin-1.0.1.dist-info/METADATA
hydra_moai_searchpath_plugin-1.0.1.dist-info/WHEEL
hydra_moai_searchpath_plugin-1.0.1.dist-info/top_level.txt
hydra_moai_searchpath_plugin-1.0.1.dist-info/RECORD
