Metadata-Version: 2.1
Name: hydra-moai-searchpath-plugin
Version: 1.0.1
Summary: moai Hydra SearchPath plugin
Home-page: https://github.com/ai-in-motion/moai
Author: AI-in-Motion Team
Author-email: moai@ai-in-motion.dev
License: UNKNOWN
Platform: UNKNOWN
Classifier: Development Status :: 3 - Alpha
Classifier: Intended Audience :: Developers
Classifier: Intended Audience :: Science/Research
Classifier: Programming Language :: Python :: 3.7
Classifier: License :: OSI Approved :: Apache Software License
Classifier: Operating System :: OS Independent
Classifier: Topic :: Scientific/Engineering :: Artificial Intelligence
Classifier: Topic :: Software Development :: Libraries
Classifier: Topic :: Software Development :: Libraries :: Python Modules
Requires-Dist: hydra-core (==1.0.*)
Requires-Dist: moai-mdk
